tensorshare/__init__.py
tensorshare/client.py
tensorshare/import_utils.py
tensorshare/logging.py
tensorshare/logging.pyi
tensorshare/py.typed
tensorshare/schema.py
tensorshare/server.py
tensorshare/utils.py
tensorshare/serialization/__init__.py
tensorshare/serialization/constants.py
tensorshare/serialization/flax.py
tensorshare/serialization/numpy.py
tensorshare/serialization/paddle.py
tensorshare/serialization/processor.py
tensorshare/serialization/tensorflow.py
tensorshare/serialization/torch.py
tensorshare-0.1.1.dist-info/METADATA
tensorshare-0.1.1.dist-info/WHEEL
tensorshare-0.1.1.dist-info/licenses/LICENSE
tensorshare-0.1.1.dist-info/RECORD
