Metadata-Version: 2.1
Name: tensorshare
Version: 0.1.1
Summary: 🤝 Trade any tensors over the network
Project-URL: Documentation, https://chainyo.github.io/tensorshare
Project-URL: Issues, https://github.com/chainyo/tensorshare/issues
Project-URL: Source, https://github.com/chainyo/tensorshare
Author-email: Thomas Chaigneau <t.chaigneau.tc@gmail.com>
License-Expression: MIT
License-File: LICENSE
Keywords: artificial intelligence,deep learning,fastapi,jax,machine-learning,network,numpy,paddlepaddle,pydantic,pytorch,safetensors,tensorflow
Classifier: Development Status :: 4 - Beta
Classifier: Intended Audience :: Developers
Classifier: License :: OSI Approved :: MIT License
Classifier: Programming Language :: Python
Classifier: Programming Language :: Python :: 3 :: Only
Classifier: Programming Language :: Python :: 3.8
Classifier: Programming Language :: Python :: 3.9
Classifier: Programming Language :: Python :: 3.10
Classifier: Programming Language :: Python :: 3.11
Classifier: Programming Language :: Python :: Implementation :: CPython
Classifier: Programming Language :: Python :: Implementation :: PyPy
Classifier: Topic :: Internet
Classifier: Topic :: Software Development
Classifier: Topic :: Software Development :: Libraries
Classifier: Topic :: Software Development :: Libraries :: Application Frameworks
Classifier: Topic :: Software Development :: Libraries :: Python Modules
Requires-Python: <3.12,>=3.8
Requires-Dist: pydantic>=2.1.1
Requires-Dist: safetensors>=0.3.1
Provides-Extra: all
Requires-Dist: aiohttp>=3.8.5; extra == 'all'
Requires-Dist: fastapi>=0.101.1; extra == 'all'
Requires-Dist: flax>=0.6.3; extra == 'all'
Requires-Dist: jax<0.4.14; extra == 'all'
Requires-Dist: jaxlib<0.4.14; extra == 'all'
Requires-Dist: numpy>=1.21.6; extra == 'all'
Requires-Dist: paddlepaddle>=2.4.1; extra == 'all'
Requires-Dist: torch>=1.10; extra == 'all'
Provides-Extra: client
Requires-Dist: aiohttp>=3.8.5; extra == 'client'
Provides-Extra: dev
Requires-Dist: black>=22.10.0; extra == 'dev'
Requires-Dist: fastapi>=0.101.1; extra == 'dev'
Requires-Dist: flax>=0.6.3; extra == 'dev'
Requires-Dist: jax<0.4.14; extra == 'dev'
Requires-Dist: jaxlib<0.4.14; extra == 'dev'
Requires-Dist: mkdocs-git-revision-date-localized-plugin>=1.1.0; extra == 'dev'
Requires-Dist: mkdocs-material>=8.5.4; extra == 'dev'
Requires-Dist: mkdocs>=1.4.0; extra == 'dev'
Requires-Dist: mkdocstrings[python]>=0.20.0; extra == 'dev'
Requires-Dist: numpy>=1.21.6; extra == 'dev'
Requires-Dist: paddlepaddle>=2.4.1; extra == 'dev'
Requires-Dist: pre-commit>=2.20.0; extra == 'dev'
Requires-Dist: pytest-cov>=4.1; extra == 'dev'
Requires-Dist: pytest>=7.4; extra == 'dev'
Requires-Dist: ruff>=0.0.263; extra == 'dev'
Requires-Dist: torch>=1.10; extra == 'dev'
Provides-Extra: docs
Requires-Dist: mkdocs-git-revision-date-localized-plugin>=1.1.0; extra == 'docs'
Requires-Dist: mkdocs-material>=8.5.4; extra == 'docs'
Requires-Dist: mkdocs>=1.4.0; extra == 'docs'
Requires-Dist: mkdocstrings[python]>=0.20.0; extra == 'docs'
Provides-Extra: jax
Requires-Dist: flax>=0.6.3; extra == 'jax'
Requires-Dist: jax<0.4.14; extra == 'jax'
Requires-Dist: jaxlib<0.4.14; extra == 'jax'
Requires-Dist: numpy>=1.21.6; extra == 'jax'
Provides-Extra: numpy
Requires-Dist: numpy>=1.21.6; extra == 'numpy'
Provides-Extra: paddlepaddle
Requires-Dist: numpy>=1.21.6; extra == 'paddlepaddle'
Requires-Dist: paddlepaddle>=2.4.1; extra == 'paddlepaddle'
Provides-Extra: quality
Requires-Dist: black>=22.10.0; extra == 'quality'
Requires-Dist: mypy>=1.4; extra == 'quality'
Requires-Dist: pre-commit>=2.20.0; extra == 'quality'
Requires-Dist: ruff>=0.0.263; extra == 'quality'
Provides-Extra: server
Requires-Dist: fastapi>=0.101.1; extra == 'server'
Provides-Extra: tests
Requires-Dist: aiohttp>=3.8.5; extra == 'tests'
Requires-Dist: aioresponses>=0.7.4; extra == 'tests'
Requires-Dist: fastapi>=0.101.1; extra == 'tests'
Requires-Dist: flax>=0.6.3; extra == 'tests'
Requires-Dist: httpx>=0.23.0; extra == 'tests'
Requires-Dist: jax<0.4.14; extra == 'tests'
Requires-Dist: jaxlib<0.4.14; extra == 'tests'
Requires-Dist: numpy>=1.21.6; extra == 'tests'
Requires-Dist: paddlepaddle>=2.4.1; extra == 'tests'
Requires-Dist: pytest-asyncio>=0.21.1; extra == 'tests'
Requires-Dist: pytest-cov>=4.1; extra == 'tests'
Requires-Dist: pytest>=7.4; extra == 'tests'
Requires-Dist: torch>=1.10; extra == 'tests'
Provides-Extra: torch
Requires-Dist: numpy>=1.21.6; extra == 'torch'
Requires-Dist: torch>=1.10; extra == 'torch'
